LICENSE
MANIFEST.in
README.md
setup.cfg
setup.py
tap_gitlab/__init__.py
tap_gitlab.egg-info/PKG-INFO
tap_gitlab.egg-info/SOURCES.txt
tap_gitlab.egg-info/dependency_links.txt
tap_gitlab.egg-info/entry_points.txt
tap_gitlab.egg-info/requires.txt
tap_gitlab.egg-info/top_level.txt
tap_gitlab/schemas/branches.json
tap_gitlab/schemas/commits.json
tap_gitlab/schemas/groups.json
tap_gitlab/schemas/issues.json
tap_gitlab/schemas/milestones.json
tap_gitlab/schemas/projects.json
tap_gitlab/schemas/users.json