Metadata-Version: 1.1
Name: tap-gitlab
Version: 0.5.0
Summary: Singer.io tap for extracting data from the GitLab API
Home-page: https://singer.io
Author: Stitch
Author-email: UNKNOWN
License: UNKNOWN
Platform: UNKNOWN
Classifier: Programming Language :: Python :: 3 :: Only
